{
  "meta": {
    "source": "TD_Scrape",
    "source_url": "https://www.tesourodireto.com.br/documents/d/guest/rendimento-resgatar-csv?download=true",
    "last_run_at": "2026-03-04T11:46:11-03:00",
    "last_price_change_at": "2026-03-04T09:33:01.737-03:00",
    "rows": 60
  },
  "data": [
    {
      "Ticker": "LFT 2027-03-01",
      "Preco_Atual": 18506.44,
      "Yield_Atual": 0.0157
    },
    {
      "Ticker": "LFT 2028-03-01",
      "Preco_Atual": 18493.61,
      "Yield_Atual": 0.0428
    },
    {
      "Ticker": "LFT 2029-03-01",
      "Preco_Atual": 18471.42,
      "Yield_Atual": 0.0691
    },
    {
      "Ticker": "LFT 2031-03-01",
      "Preco_Atual": 18409.69,
      "Yield_Atual": 0.109
    },
    {
      "Ticker": "NTN-F 2027-01-01",
      "Preco_Atual": 992.14,
      "Yield_Atual": 13.42
    },
    {
      "Ticker": "LTN 2027-01-01",
      "Preco_Atual": 901.41,
      "Yield_Atual": 13.4
    },
    {
      "Ticker": "LTN 2028-01-01",
      "Preco_Atual": 801.71,
      "Yield_Atual": 12.9
    },
    {
      "Ticker": "NTN-F 2029-01-01",
      "Preco_Atual": 951.79,
      "Yield_Atual": 13.05
    },
    {
      "Ticker": "LTN 2029-01-01",
      "Preco_Atual": 709.01,
      "Yield_Atual": 13.04
    },
    {
      "Ticker": "NTN-F 2031-01-01",
      "Preco_Atual": 902.91,
      "Yield_Atual": 13.53
    },
    {
      "Ticker": "LTN 2031-01-01",
      "Preco_Atual": 546.11,
      "Yield_Atual": 13.45
    },
    {
      "Ticker": "LTN 2032-01-01",
      "Preco_Atual": 476.97,
      "Yield_Atual": 13.63
    },
    {
      "Ticker": "NTN-F 2033-01-01",
      "Preco_Atual": 864.83,
      "Yield_Atual": 13.72
    },
    {
      "Ticker": "NTN-F 2035-01-01",
      "Preco_Atual": 841.09,
      "Yield_Atual": 13.71
    },
    {
      "Ticker": "NTN-F 2037-01-01",
      "Preco_Atual": 817.97,
      "Yield_Atual": 13.8
    },
    {
      "Ticker": "NTN-B P 2026-08-15",
      "Preco_Atual": 4420.89,
      "Yield_Atual": 10.13
    },
    {
      "Ticker": "NTN-B 2026-08-15",
      "Preco_Atual": 4551.58,
      "Yield_Atual": 10.13
    },
    {
      "Ticker": "NTN-B P 2029-05-15",
      "Preco_Atual": 3652.4,
      "Yield_Atual": 7.69
    },
    {
      "Ticker": "NTN-B 2030-08-15",
      "Preco_Atual": 4354.71,
      "Yield_Atual": 7.73
    },
    {
      "Ticker": "NTN-B P 2032-08-15",
      "Preco_Atual": 2885.39,
      "Yield_Atual": 7.61
    },
    {
      "Ticker": "NTN-B 2032-08-15",
      "Preco_Atual": 4272.3,
      "Yield_Atual": 7.64
    },
    {
      "Ticker": "NTN-B P 2035-05-15",
      "Preco_Atual": 2401.63,
      "Yield_Atual": 7.42
    },
    {
      "Ticker": "NTN-B 2035-05-15",
      "Preco_Atual": 4277.75,
      "Yield_Atual": 7.48
    },
    {
      "Ticker": "NTN-B 2037-05-15",
      "Preco_Atual": 4229.46,
      "Yield_Atual": 7.44
    },
    {
      "Ticker": "NTN-B P 2040-08-15",
      "Preco_Atual": 1709.71,
      "Yield_Atual": 7.16
    },
    {
      "Ticker": "NTN-B 2040-08-15",
      "Preco_Atual": 4137.31,
      "Yield_Atual": 7.28
    },
    {
      "Ticker": "NTN-B P 2045-05-15",
      "Preco_Atual": 1267.85,
      "Yield_Atual": 7.01
    },
    {
      "Ticker": "NTN-B 2045-05-15",
      "Preco_Atual": 4173.44,
      "Yield_Atual": 7.17
    },
    {
      "Ticker": "NTN-B P 2050-08-15",
      "Preco_Atual": 912.8,
      "Yield_Atual": 6.9
    },
    {
      "Ticker": "NTN-B 2050-08-15",
      "Preco_Atual": 4079.41,
      "Yield_Atual": 7.1
    },
    {
      "Ticker": "NTN-B 2055-05-15",
      "Preco_Atual": 4122.56,
      "Yield_Atual": 7.08
    },
    {
      "Ticker": "NTN-B 2060-08-15",
      "Preco_Atual": 4020.76,
      "Yield_Atual": 7.09
    },
    {
      "Ticker": "NTN-B1 R+ 2049-12-15",
      "Preco_Atual": 1917.44,
      "Yield_Atual": 7.22
    },
    {
      "Ticker": "NTN-B1 R+ 2054-12-15",
      "Preco_Atual": 1385.54,
      "Yield_Atual": 7.08
    },
    {
      "Ticker": "NTN-B1 R+ 2059-12-15",
      "Preco_Atual": 1008.22,
      "Yield_Atual": 6.97
    },
    {
      "Ticker": "NTN-B1 R+ 2064-12-15",
      "Preco_Atual": 730.42,
      "Yield_Atual": 6.92
    },
    {
      "Ticker": "NTN-B1 R+ 2069-12-15",
      "Preco_Atual": 525.34,
      "Yield_Atual": 6.91
    },
    {
      "Ticker": "NTN-B1 R+ 2074-12-15",
      "Preco_Atual": 375.6,
      "Yield_Atual": 6.92
    },
    {
      "Ticker": "NTN-B1 R+ 2079-12-15",
      "Preco_Atual": 268.28,
      "Yield_Atual": 6.93
    },
    {
      "Ticker": "NTN-B1 R+ 2084-12-15",
      "Preco_Atual": 192.3,
      "Yield_Atual": 6.93
    },
    {
      "Ticker": "NTN-B1 E+ 2030-12-15",
      "Preco_Atual": 3746.35,
      "Yield_Atual": 7.86
    },
    {
      "Ticker": "NTN-B1 E+ 2031-12-15",
      "Preco_Atual": 3630.78,
      "Yield_Atual": 7.75
    },
    {
      "Ticker": "NTN-B1 E+ 2032-12-15",
      "Preco_Atual": 3380.17,
      "Yield_Atual": 7.68
    },
    {
      "Ticker": "NTN-B1 E+ 2033-12-15",
      "Preco_Atual": 3147.99,
      "Yield_Atual": 7.63
    },
    {
      "Ticker": "NTN-B1 E+ 2034-12-15",
      "Preco_Atual": 2933.93,
      "Yield_Atual": 7.58
    },
    {
      "Ticker": "NTN-B1 E+ 2035-12-15",
      "Preco_Atual": 2737.1,
      "Yield_Atual": 7.53
    },
    {
      "Ticker": "NTN-B1 E+ 2036-12-15",
      "Preco_Atual": 2556.03,
      "Yield_Atual": 7.48
    },
    {
      "Ticker": "NTN-B1 E+ 2037-12-15",
      "Preco_Atual": 2387.29,
      "Yield_Atual": 7.44
    },
    {
      "Ticker": "NTN-B1 E+ 2038-12-15",
      "Preco_Atual": 2233.84,
      "Yield_Atual": 7.39
    },
    {
      "Ticker": "NTN-B1 E+ 2039-12-15",
      "Preco_Atual": 2092.15,
      "Yield_Atual": 7.34
    },
    {
      "Ticker": "NTN-B1 E+ 2040-12-15",
      "Preco_Atual": 1960.82,
      "Yield_Atual": 7.29
    },
    {
      "Ticker": "NTN-B1 E+ 2041-12-15",
      "Preco_Atual": 1841.63,
      "Yield_Atual": 7.23
    },
    {
      "Ticker": "NTN-B1 E+ 2042-12-15",
      "Preco_Atual": 1729.36,
      "Yield_Atual": 7.18
    },
    {
      "Ticker": "NTN-B1 E+ 2043-12-15",
      "Preco_Atual": 1625.31,
      "Yield_Atual": 7.13
    },
    {
      "Ticker": "NTN-B1 E+ 2044-12-15",
      "Preco_Atual": 1526.76,
      "Yield_Atual": 7.09
    },
    {
      "Ticker": "NTN-B1 E+ 2045-12-15",
      "Preco_Atual": 1433.08,
      "Yield_Atual": 7.06
    },
    {
      "Ticker": "NTN-B1 E+ 2046-12-15",
      "Preco_Atual": 1345.99,
      "Yield_Atual": 7.03
    },
    {
      "Ticker": "NTN-B1 E+ 2047-12-15",
      "Preco_Atual": 1262.74,
      "Yield_Atual": 7.01
    },
    {
      "Ticker": "NTN-B1 E+ 2048-12-15",
      "Preco_Atual": 1187.31,
      "Yield_Atual": 6.98
    },
    {
      "Ticker": "NTN-C 2031-01-01",
      "Preco_Atual": 7536.05,
      "Yield_Atual": 8.02
    }
  ]
}