{
  "meta": {
    "source": "TD_Scrape",
    "source_url": "https://www.tesourodireto.com.br/documents/d/guest/rendimento-resgatar-csv?download=true",
    "last_run_at": "2026-02-11T10:46:13-03:00",
    "last_price_change_at": "2026-02-11T09:29:22.047-03:00",
    "rows": 61
  },
  "data": [
    {
      "Ticker": "LFT 2026-03-01",
      "Preco_Atual": 18376.74,
      "Yield_Atual": 0.049
    },
    {
      "Ticker": "LFT 2027-03-01",
      "Preco_Atual": 18372.97,
      "Yield_Atual": 0.022
    },
    {
      "Ticker": "LFT 2028-03-01",
      "Preco_Atual": 18358.07,
      "Yield_Atual": 0.0511
    },
    {
      "Ticker": "LFT 2029-03-01",
      "Preco_Atual": 18336.07,
      "Yield_Atual": 0.0742
    },
    {
      "Ticker": "LFT 2031-03-01",
      "Preco_Atual": 18276.31,
      "Yield_Atual": 0.11
    },
    {
      "Ticker": "NTN-F 2027-01-01",
      "Preco_Atual": 985.94,
      "Yield_Atual": 13.39
    },
    {
      "Ticker": "LTN 2027-01-01",
      "Preco_Atual": 895.58,
      "Yield_Atual": 13.4
    },
    {
      "Ticker": "LTN 2028-01-01",
      "Preco_Atual": 798.56,
      "Yield_Atual": 12.76
    },
    {
      "Ticker": "NTN-F 2029-01-01",
      "Preco_Atual": 949.38,
      "Yield_Atual": 12.88
    },
    {
      "Ticker": "LTN 2029-01-01",
      "Preco_Atual": 707.4,
      "Yield_Atual": 12.88
    },
    {
      "Ticker": "NTN-F 2031-01-01",
      "Preco_Atual": 901.6,
      "Yield_Atual": 13.38
    },
    {
      "Ticker": "LTN 2031-01-01",
      "Preco_Atual": 546.06,
      "Yield_Atual": 13.3
    },
    {
      "Ticker": "LTN 2032-01-01",
      "Preco_Atual": 477.26,
      "Yield_Atual": 13.49
    },
    {
      "Ticker": "NTN-F 2033-01-01",
      "Preco_Atual": 863.21,
      "Yield_Atual": 13.61
    },
    {
      "Ticker": "NTN-F 2035-01-01",
      "Preco_Atual": 839.33,
      "Yield_Atual": 13.62
    },
    {
      "Ticker": "NTN-F 2037-01-01",
      "Preco_Atual": 815.7,
      "Yield_Atual": 13.73
    },
    {
      "Ticker": "NTN-B P 2026-08-15",
      "Preco_Atual": 4375.67,
      "Yield_Atual": 10.35
    },
    {
      "Ticker": "NTN-B 2026-08-15",
      "Preco_Atual": 4640.81,
      "Yield_Atual": 10.35
    },
    {
      "Ticker": "NTN-B P 2029-05-15",
      "Preco_Atual": 3614.21,
      "Yield_Atual": 7.77
    },
    {
      "Ticker": "NTN-B 2030-08-15",
      "Preco_Atual": 4444.11,
      "Yield_Atual": 7.8
    },
    {
      "Ticker": "NTN-B P 2032-08-15",
      "Preco_Atual": 2841.62,
      "Yield_Atual": 7.73
    },
    {
      "Ticker": "NTN-B 2032-08-15",
      "Preco_Atual": 4348.22,
      "Yield_Atual": 7.76
    },
    {
      "Ticker": "NTN-B P 2035-05-15",
      "Preco_Atual": 2352.17,
      "Yield_Atual": 7.57
    },
    {
      "Ticker": "NTN-B 2035-05-15",
      "Preco_Atual": 4205.23,
      "Yield_Atual": 7.62
    },
    {
      "Ticker": "NTN-B 2037-05-15",
      "Preco_Atual": 4146.14,
      "Yield_Atual": 7.6
    },
    {
      "Ticker": "NTN-B P 2040-08-15",
      "Preco_Atual": 1653.54,
      "Yield_Atual": 7.35
    },
    {
      "Ticker": "NTN-B 2040-08-15",
      "Preco_Atual": 4175.23,
      "Yield_Atual": 7.46
    },
    {
      "Ticker": "NTN-B P 2045-05-15",
      "Preco_Atual": 1213.86,
      "Yield_Atual": 7.21
    },
    {
      "Ticker": "NTN-B 2045-05-15",
      "Preco_Atual": 4061.17,
      "Yield_Atual": 7.36
    },
    {
      "Ticker": "NTN-B P 2050-08-15",
      "Preco_Atual": 861.53,
      "Yield_Atual": 7.12
    },
    {
      "Ticker": "NTN-B 2050-08-15",
      "Preco_Atual": 4091.12,
      "Yield_Atual": 7.3
    },
    {
      "Ticker": "NTN-B 2055-05-15",
      "Preco_Atual": 4012.31,
      "Yield_Atual": 7.24
    },
    {
      "Ticker": "NTN-B 2060-08-15",
      "Preco_Atual": 4039.63,
      "Yield_Atual": 7.26
    },
    {
      "Ticker": "NTN-B1 R+ 2049-12-15",
      "Preco_Atual": 1865.89,
      "Yield_Atual": 7.4
    },
    {
      "Ticker": "NTN-B1 R+ 2054-12-15",
      "Preco_Atual": 1335,
      "Yield_Atual": 7.27
    },
    {
      "Ticker": "NTN-B1 R+ 2059-12-15",
      "Preco_Atual": 964.81,
      "Yield_Atual": 7.15
    },
    {
      "Ticker": "NTN-B1 R+ 2064-12-15",
      "Preco_Atual": 694.86,
      "Yield_Atual": 7.09
    },
    {
      "Ticker": "NTN-B1 R+ 2069-12-15",
      "Preco_Atual": 497.29,
      "Yield_Atual": 7.07
    },
    {
      "Ticker": "NTN-B1 R+ 2074-12-15",
      "Preco_Atual": 354.12,
      "Yield_Atual": 7.07
    },
    {
      "Ticker": "NTN-B1 R+ 2079-12-15",
      "Preco_Atual": 251.18,
      "Yield_Atual": 7.08
    },
    {
      "Ticker": "NTN-B1 R+ 2084-12-15",
      "Preco_Atual": 178.79,
      "Yield_Atual": 7.08
    },
    {
      "Ticker": "NTN-B1 E+ 2030-12-15",
      "Preco_Atual": 3784.42,
      "Yield_Atual": 7.96
    },
    {
      "Ticker": "NTN-B1 E+ 2031-12-15",
      "Preco_Atual": 3590.65,
      "Yield_Atual": 7.85
    },
    {
      "Ticker": "NTN-B1 E+ 2032-12-15",
      "Preco_Atual": 3339.83,
      "Yield_Atual": 7.78
    },
    {
      "Ticker": "NTN-B1 E+ 2033-12-15",
      "Preco_Atual": 3106.12,
      "Yield_Atual": 7.74
    },
    {
      "Ticker": "NTN-B1 E+ 2034-12-15",
      "Preco_Atual": 2888.7,
      "Yield_Atual": 7.71
    },
    {
      "Ticker": "NTN-B1 E+ 2035-12-15",
      "Preco_Atual": 2689.92,
      "Yield_Atual": 7.67
    },
    {
      "Ticker": "NTN-B1 E+ 2036-12-15",
      "Preco_Atual": 2506.86,
      "Yield_Atual": 7.63
    },
    {
      "Ticker": "NTN-B1 E+ 2037-12-15",
      "Preco_Atual": 2338.16,
      "Yield_Atual": 7.59
    },
    {
      "Ticker": "NTN-B1 E+ 2038-12-15",
      "Preco_Atual": 2182.81,
      "Yield_Atual": 7.55
    },
    {
      "Ticker": "NTN-B1 E+ 2039-12-15",
      "Preco_Atual": 2039.26,
      "Yield_Atual": 7.51
    },
    {
      "Ticker": "NTN-B1 E+ 2040-12-15",
      "Preco_Atual": 1906.11,
      "Yield_Atual": 7.47
    },
    {
      "Ticker": "NTN-B1 E+ 2041-12-15",
      "Preco_Atual": 1785.1,
      "Yield_Atual": 7.42
    },
    {
      "Ticker": "NTN-B1 E+ 2042-12-15",
      "Preco_Atual": 1673.34,
      "Yield_Atual": 7.37
    },
    {
      "Ticker": "NTN-B1 E+ 2043-12-15",
      "Preco_Atual": 1567.69,
      "Yield_Atual": 7.33
    },
    {
      "Ticker": "NTN-B1 E+ 2044-12-15",
      "Preco_Atual": 1469.92,
      "Yield_Atual": 7.29
    },
    {
      "Ticker": "NTN-B1 E+ 2045-12-15",
      "Preco_Atual": 1377.17,
      "Yield_Atual": 7.26
    },
    {
      "Ticker": "NTN-B1 E+ 2046-12-15",
      "Preco_Atual": 1288.91,
      "Yield_Atual": 7.24
    },
    {
      "Ticker": "NTN-B1 E+ 2047-12-15",
      "Preco_Atual": 1208.99,
      "Yield_Atual": 7.21
    },
    {
      "Ticker": "NTN-B1 E+ 2048-12-15",
      "Preco_Atual": 1132.55,
      "Yield_Atual": 7.19
    },
    {
      "Ticker": "NTN-C 2031-01-01",
      "Preco_Atual": 7553.73,
      "Yield_Atual": 8.06
    }
  ]
}